[
	{
		"label": 1,
		"inputSeries": [
			{
				"inputData": [ 185.67486572265625, -315.04129028320313 ]
			}
		]
	},
	{
		"label": 1,
		"inputSeries": [
			{
				"inputData": [ 35.742465972900391, -234.8507080078125 ]
			}
		]
	},
	{
		"label": 1,
		"inputSeries": [
			{
				"inputData": [ -222.91827392578125, -254.15077209472656 ]
			}
		]
	},
	{
		"label": 2,
		"inputSeries": [
			{
				"inputData": [ -199.31573486328125, -12.49852180480957 ]
			}
		]
	},
	{
		"label": 2,
		"inputSeries": [
			{
				"inputData": [ -37.577079772949219, 31.509899139404297 ]
			}
		]
	},
	{
		"label": 2,
		"inputSeries": [
			{
				"inputData": [ 106.03270721435547, -81.7215576171875 ]
			}
		]
	},
	{
		"label": 3,
		"inputSeries": [
			{
				"inputData": [ 280.29318237304688, 258.52328491210938 ]
			}
		]
	},
	{
		"label": 3,
		"inputSeries": [
			{
				"inputData": [ 77.428047180175781, 335.7569580078125 ]
			}
		]
	},
	{
		"label": 3,
		"inputSeries": [
			{
				"inputData": [ -185.40238952636719, 386.54766845703125 ]
			}
		]
	}
]